core/__init__.py
core/decorators.py
core/directory.py
core/renamer.py
core/version.py
util/__init__.py
util/directedgraph.py
util/util.py
renamer_kt-1.0.2.dist-info/LICENSE
renamer_kt-1.0.2.dist-info/METADATA
renamer_kt-1.0.2.dist-info/WHEEL
renamer_kt-1.0.2.dist-info/entry_points.txt
renamer_kt-1.0.2.dist-info/top_level.txt
renamer_kt-1.0.2.dist-info/zip-safe
renamer_kt-1.0.2.dist-info/RECORD
