Metadata-Version: 2.1
Name: renamer_kt
Version: 1.0.2
Summary: CLI tool written in Python 3 used to systemically rename files in a directory while adhering to a variety of criteria.
Home-page: https://github.com/KevinTyrrell/renamer
Author: Kevin Tyrrell
Author-email: KevinTearUl@gmail.com
License: GPL-3.0
Keywords: file renaming,CLI tool,Python 3,naming schemes,file organization,file sorting,file management,batch renaming,file renaming tool
Classifier: License :: OSI Approved :: GNU General Public License v3 (GPLv3)
Classifier: Development Status :: 4 - Beta
Classifier: Intended Audience :: Developers
Classifier: Programming Language :: Python
Classifier: Programming Language :: Python :: 3
Classifier: Programming Language :: Python :: Implementation :: CPython
Classifier: Programming Language :: Python :: Implementation :: PyPy
Requires-Python: >=3
License-File: LICENSE
